Metadata-Version: 2.1
Name: treeds
Version: 0.0.1
Summary: Simple implementation of Tree Data Structure
Home-page: UNKNOWN
License: UNKNOWN
Keywords: python,treeds,tree python,data structure,tree data structure,pytree
Platform: UNKNOWN
Classifier: Development Status :: 1 - Planning
Classifier: Intended Audience :: Developers
Classifier: Programming Language :: Python :: 3
Classifier: Operating System :: Unix
Classifier: Operating System :: MacOS :: MacOS X
Classifier: Operating System :: Microsoft :: Windows
